optyx/__init__.py
optyx/analysis.py
optyx/constraints.py
optyx/core/__init__.py
optyx/core/autodiff.py
optyx/core/compiler.py
optyx/core/errors.py
optyx/core/expressions.py
optyx/core/functions.py
optyx/core/matrices.py
optyx/core/parameters.py
optyx/core/vectors.py
optyx/core/verification.py
optyx/problem.py
optyx/py.typed
optyx/solution.py
optyx/solvers/__init__.py
optyx/solvers/lp_solver.py
optyx/solvers/scipy_solver.py
optyx-1.2.2.dist-info/WHEEL
optyx-1.2.2.dist-info/METADATA
optyx-1.2.2.dist-info/RECORD
