Metadata-Version: 2.4
Name: optyx
Version: 1.2.2
Summary: Intuitive symbolic interface for constrained optimization problems
Keywords: optimization,autodiff,symbolic,automatic-differentiation,gradient,constraints,mathematical-optimization
Author: Dagmawi B. Tadesse
Author-email: Dagmawi B. Tadesse <daggbt@gmail.com>
License-Expression: MIT
Classifier: Development Status :: 3 - Alpha
Classifier: Intended Audience :: Developers
Classifier: Intended Audience :: Science/Research
Classifier: License :: OSI Approved :: MIT License
Classifier: Operating System :: OS Independent
Classifier: Programming Language :: Python :: 3
Classifier: Programming Language :: Python :: 3.10
Classifier: Programming Language :: Python :: 3.11
Classifier: Programming Language :: Python :: 3.12
Classifier: Topic :: Scientific/Engineering :: Mathematics
Classifier: Topic :: Software Development :: Libraries :: Python Modules
Classifier: Typing :: Typed
Requires-Dist: numpy>=1.22
Requires-Dist: scipy>=1.8
Requires-Dist: cvxpy>=1.4.0 ; extra == 'benchmarks'
Requires-Dist: matplotlib>=3.10.0 ; extra == 'benchmarks'
Requires-Dist: pyomo>=6.7.0 ; extra == 'benchmarks'
Requires-Python: >=3.10
Project-URL: Homepage, https://daggbt.github.io/optyx/
Project-URL: Documentation, https://daggbt.github.io/optyx/
Project-URL: Repository, https://github.com/daggbt/optyx
Project-URL: Changelog, https://github.com/daggbt/optyx/blob/main/CHANGELOG.md
Project-URL: Issues, https://github.com/daggbt/optyx/issues
Provides-Extra: benchmarks
